Metadata-Version: 2.4
Name: esgpull-plus
Version: 0.0.3
Summary: Extension of the original ESGF data discovery, download, replication package, esgpull
Project-URL: Repository, https://github.com/orlando-code/esgpull-plus
Project-URL: Documentation, https://github.com/orlando-code/esgpull-plus
Project-URL: Issues, https://github.com/orlando-code/esgpull-plus/issues
Project-URL: Changelog, https://github.com/orlando-code/esgpull-plus/blob/main/CHANGELOG.md
Project-URL: Original_respository, https://github.com/ESGF/esgf-download
Project-URL: Original_documentation, https://esgf.github.io/esgf-download/
Author-email: Orlando Timmerman <rt582@cam.ac.uk>
License: BSD-3-Clause
License-File: LICENSE
Classifier: Development Status :: 3 - Alpha
Classifier: Intended Audience :: Science/Research
Classifier: License :: OSI Approved :: BSD License
Classifier: Programming Language :: Python :: 3
Classifier: Programming Language :: Python :: 3.10
Classifier: Programming Language :: Python :: 3.11
Classifier: Programming Language :: Python :: 3.12
Classifier: Programming Language :: Python :: 3.13
Requires-Python: >=3.10
Requires-Dist: aiofiles>=22.1.0
Requires-Dist: aiostream>=0.4.5
Requires-Dist: alembic>=1.8.1
Requires-Dist: attrs>=22.1.0
Requires-Dist: cattrs>=22.2.0
Requires-Dist: click-params>=0.4.0
Requires-Dist: click>=8.1.3
Requires-Dist: httpx>=0.23.0
Requires-Dist: nest-asyncio>=1.5.6
Requires-Dist: numpy>=1.24.0
Requires-Dist: orjson>=3.8.0
Requires-Dist: packaging>=25.0
Requires-Dist: pandas>=2.0.0
Requires-Dist: platformdirs>=2.6.2
Requires-Dist: pydantic-settings>=2.10.1
Requires-Dist: pydantic>=2.11.7
Requires-Dist: pyopenssl>=22.1.0
Requires-Dist: pyparsing>=3.0.9
Requires-Dist: pyyaml>=6.0
Requires-Dist: requests>=2.28.0
Requires-Dist: rich>=12.6.0
Requires-Dist: setuptools>=65.4.1
Requires-Dist: sqlalchemy>=2.0.0b2
Requires-Dist: tomlkit>=0.11.5
Requires-Dist: watchdog>=3.0.0
Requires-Dist: xarray>=2023.1.0
